README.txt
setup.py
docs/HISTORY.txt
docs/LICENSE.GPL
docs/LICENSE.txt
docs/jquery-tools-license.txt
plone/__init__.py
plone.app.jqtools.egg-info/PKG-INFO
plone.app.jqtools.egg-info/SOURCES.txt
plone.app.jqtools.egg-info/dependency_links.txt
plone.app.jqtools.egg-info/entry_points.txt
plone.app.jqtools.egg-info/namespace_packages.txt
plone.app.jqtools.egg-info/not-zip-safe
plone.app.jqtools.egg-info/requires.txt
plone.app.jqtools.egg-info/top_level.txt
plone/app/__init__.py
plone/app/jqtools/__init__.py