Metadata-Version: 1.0
Name: plone.app.jqtools
Version: 1.0
Summary: JQuery Tools Integration for Plone
Home-page: http://svn.plone.org/svn/plone/plone.app.jquerytools
Author: Plone Foundation
Author-email: plone-developers@lists.sourceforge.net
License: GPL
Keywords: Plone JQuery
Platform: UNKNOWN
Classifier: Framework :: Plone
Classifier: Programming Language :: Python
